Workbook

Sheet Como Usar
A1: 📋 COMO USAR ESTE ORÇAMENTO
A3: ESTRUTURA DA PLANILHA
A4: Resumo Anual | B4: • Visão geral de todos os meses em uma única tela.
A5: Abas Jan – Dez | B5: • Uma aba por mês com orçamento e lançamentos lado a lado.
A7: COMO PREENCHER CADA MÊS
A8: Passo 1 – Orçado | B8: • Coluna B de cada categoria: quanto você PLANEJA gastar/receber.
A9: Passo 2 – Realizado | B9: • Coluna C de cada categoria: quanto você EFETIVAMENTE gastou/recebeu.
A10: Diferença | B10: • Calculada automaticamente (Coluna D).
A11: Saldo do Mês | B11: • Calculado automaticamente: Total Receitas − Total Despesas.
A13: LANÇAMENTOS DETALHADOS (lado direito)
A14: Data | B14: • Formato DD/MM/AAAA.
A15: Descrição | B15: • Ex: 'Conta de luz', 'Salário março'.
A16: Categoria | B16: • Selecione da lista suspensa.
A17: Tipo | B17: • Selecione: Receita ou Despesa.
A18: Valor (R$) | B18: • Sempre positivo.
A20: DICAS
A21: Saldo verde | B21: • Receitas > Despesas — ótimo!
A22: Saldo vermelho | B22: • Despesas > Receitas — revise o orçamento.
A23: Acumulado | B23: • Linha 'Saldo Acumulado' no Resumo mostra o crescimento ao longo do ano.

Sheet Resumo Anual
A1: RESUMO ANUAL 2026 — ORÇAMENTO FINANCEIRO
A2: Valores Realizados por Categoria • Coluna C de cada mês
A3: Categoria | B3: Jan | C3: Fev | D3: Mar | E3: Abr | F3: Mai | G3: Jun | H3: Jul | I3: Ago | J3: Set | K3: Out | L3: Nov | M3: Dez | N3: TOTAL ANUAL
A4: RECEITAS
A5: Salário | B5: ='Jan'!C5 | C5: ='Fev'!C5 | D5: ='Mar'!C5 | E5: ='Abr'!C5 | F5: ='Mai'!C5 | G5: ='Jun'!C5 | H5: ='Jul'!C5 | I5: ='Ago'!C5 | J5: ='Set'!C5 | K5: ='Out'!C5 | L5: ='Nov'!C5 | M5: ='Dez'!C5 | N5: =SUM(B5:M5)
A6: Freelance / Extra | B6: ='Jan'!C6 | C6: ='Fev'!C6 | D6: ='Mar'!C6 | E6: ='Abr'!C6 | F6: ='Mai'!C6 | G6: ='Jun'!C6 | H6: ='Jul'!C6 | I6: ='Ago'!C6 | J6: ='Set'!C6 | K6: ='Out'!C6 | L6: ='Nov'!C6 | M6: ='Dez'!C6 | N6: =SUM(B6:M6)
A7: Investimentos | B7: ='Jan'!C7 | C7: ='Fev'!C7 | D7: ='Mar'!C7 | E7: ='Abr'!C7 | F7: ='Mai'!C7 | G7: ='Jun'!C7 | H7: ='Jul'!C7 | I7: ='Ago'!C7 | J7: ='Set'!C7 | K7: ='Out'!C7 | L7: ='Nov'!C7 | M7: ='Dez'!C7 | N7: =SUM(B7:M7)
A8: Outros (Receita) | B8: ='Jan'!C8 | C8: ='Fev'!C8 | D8: ='Mar'!C8 | E8: ='Abr'!C8 | F8: ='Mai'!C8 | G8: ='Jun'!C8 | H8: ='Jul'!C8 | I8: ='Ago'!C8 | J8: ='Set'!C8 | K8: ='Out'!C8 | L8: ='Nov'!C8 | M8: ='Dez'!C8 | N8: =SUM(B8:M8)
A9: TOTAL RECEITAS | B9: ='Jan'!C9 | C9: ='Fev'!C9 | D9: ='Mar'!C9 | E9: ='Abr'!C9 | F9: ='Mai'!C9 | G9: ='Jun'!C9 | H9: ='Jul'!C9 | I9: ='Ago'!C9 | J9: ='Set'!C9 | K9: ='Out'!C9 | L9: ='Nov'!C9 | M9: ='Dez'!C9 | N9: =SUM(B9:M9)
A11: DESPESAS
A12: Moradia + Alimentação | B12: ='Jan'!C13 | C12: ='Fev'!C13 | D12: ='Mar'!C13 | E12: ='Abr'!C13 | F12: ='Mai'!C13 | G12: ='Jun'!C13 | H12: ='Jul'!C13 | I12: ='Ago'!C13 | J12: ='Set'!C13 | K12: ='Out'!C13 | L12: ='Nov'!C13 | M12: ='Dez'!C13 | N12: =SUM(B12:M12)
A13: Transporte + Saúde | B13: ='Jan'!C14 | C13: ='Fev'!C14 | D13: ='Mar'!C14 | E13: ='Abr'!C14 | F13: ='Mai'!C14 | G13: ='Jun'!C14 | H13: ='Jul'!C14 | I13: ='Ago'!C14 | J13: ='Set'!C14 | K13: ='Out'!C14 | L13: ='Nov'!C14 | M13: ='Dez'!C14 | N13: =SUM(B13:M13)
A14: Dívidas / Parcelas | B14: ='Jan'!C15 | C14: ='Fev'!C15 | D14: ='Mar'!C15 | E14: ='Abr'!C15 | F14: ='Mai'!C15 | G14: ='Jun'!C15 | H14: ='Jul'!C15 | I14: ='Ago'!C15 | J14: ='Set'!C15 | K14: ='Out'!C15 | L14: ='Nov'!C15 | M14: ='Dez'!C15 | N14: =SUM(B14:M14)
A15: Outros (Despesa) | B15: ='Jan'!C16 | C15: ='Fev'!C16 | D15: ='Mar'!C16 | E15: ='Abr'!C16 | F15: ='Mai'!C16 | G15: ='Jun'!C16 | H15: ='Jul'!C16 | I15: ='Ago'!C16 | J15: ='Set'!C16 | K15: ='Out'!C16 | L15: ='Nov'!C16 | M15: ='Dez'!C16 | N15: =SUM(B15:M15)
A16: TOTAL DESPESAS | B16: ='Jan'!C17 | C16: ='Fev'!C17 | D16: ='Mar'!C17 | E16: ='Abr'!C17 | F16: ='Mai'!C17 | G16: ='Jun'!C17 | H16: ='Jul'!C17 | I16: ='Ago'!C17 | J16: ='Set'!C17 | K16: ='Out'!C17 | L16: ='Nov'!C17 | M16: ='Dez'!C17 | N16: =SUM(B16:M16)
A18: SALDO MENSAL (Receitas − Despesas)
A19: Saldo Realizado | B19: ='Jan'!C21 | C19: ='Fev'!C21 | D19: ='Mar'!C21 | E19: ='Abr'!C21 | F19: ='Mai'!C21 | G19: ='Jun'!C21 | H19: ='Jul'!C21 | I19: ='Ago'!C21 | J19: ='Set'!C21 | K19: ='Out'!C21 | L19: ='Nov'!C21 | M19: ='Dez'!C21 | N19: =SUM(B19:M19)
A20: Saldo Acumulado | B20: =B19 | C20: =B20+C19 | D20: =C20+D19 | E20: =D20+E19 | F20: =E20+F19 | G20: =F20+G19 | H20: =G20+H19 | I20: =H20+I19 | J20: =I20+J19 | ... M20: =L20+M19

Sheet Categorias
A1: Categorias
A2: Salário
A3: Freelance / Extra
A4: Investimentos
A5: Outros (Receita)
A6: Moradia + Alimentação
A7: Transporte + Saúde
A8: Dívidas / Parcelas
A9: Outros (Despesa)

Sheet Jan
A1: ORÇAMENTO — JANEIRO 2026 | F1: LANÇAMENTOS — JANEIRO 2026
F2: Preencha as colunas B e C (Orçado e Realizado) nos cards à esquerda
A3: ▶ RECEITAS | F3: Data | G3: Descrição | H3: Categoria | I3: Tipo | J3: Valor (R$)
A4: Categoria | B4: Orçado (R$) | C4: Realizado (R$) | D4: Diferença (R$)
A5: Salário | D5: =C5-B5
A6: Freelance / Extra | D6: =C6-B6
A7: Investimentos | D7: =C7-B7
A8: Outros (Receita) | D8: =C8-B8
A9: TOTAL RECEITAS | B9: =SUM(B5:B8) | C9: =SUM(C5:C8) | D9: =SUM(D5:D8)
A11: ▶ DESPESAS
A12: Categoria | B12: Orçado (R$) | C12: Realizado (R$) | D12: Diferença (R$)
A13: Moradia + Alimentação | D13: =B13-C13
A14: Transporte + Saúde | D14: =B14-C14
A15: Dívidas / Parcelas | D15: =B15-C15
A16: Outros (Despesa) | D16: =B16-C16
A17: TOTAL DESPESAS | B17: =SUM(B13:B16) | C17: =SUM(C13:C16) | D17: =SUM(D13:D16)
A19: ▶ SALDO DO MÊS
B20: Orçado (R$) | C20: Realizado (R$) | D20: Diferença (R$)
A21: Receitas − Despesas | B21: =B9-B17 | C21: =C9-C17 | D21: =D9-D17

Sheet Fev
A1: ORÇAMENTO — FEVEREIRO 2026 | F1: LANÇAMENTOS — FEVEREIRO 2026
F2: Preencha as colunas B e C (Orçado e Realizado) nos cards à esquerda
A3: ▶ RECEITAS | F3: Data | G3: Descrição | H3: Categoria | I3: Tipo | J3: Valor (R$)
A4: Categoria | B4: Orçado (R$) | C4: Realizado (R$) | D4: Diferença (R$)
A5: Salário | D5: =C5-B5
A6: Freelance / Extra | D6: =C6-B6
A7: Investimentos | D7: =C7-B7
A8: Outros (Receita) | D8: =C8-B8
A9: TOTAL RECEITAS | B9: =SUM(B5:B8) | C9: =SUM(C5:C8) | D9: =SUM(D5:D8)
A11: ▶ DESPESAS
A12: Categoria | B12: Orçado (R$) | C12: Realizado (R$) | D12: Diferença (R$)
A13: Moradia + Alimentação | D13: =B13-C13
A14: Transporte + Saúde | D14: =B14-C14
A15: Dívidas / Parcelas | D15: =B15-C15
A16: Outros (Despesa) | D16: =B16-C16
A17: TOTAL DESPESAS | B17: =SUM(B13:B16) | C17: =SUM(C13:C16) | D17: =SUM(D13:D16)
A19: ▶ SALDO DO MÊS
B20: Orçado (R$) | C20: Realizado (R$) | D20: Diferença (R$)
A21: Receitas − Despesas | B21: =B9-B17 | C21: =C9-C17 | D21: =D9-D17

Sheet Mar
A1: ORÇAMENTO — MARÇO 2026 | F1: LANÇAMENTOS — MARÇO 2026
F2: Preencha as colunas B e C (Orçado e Realizado) nos cards à esquerda
A3: ▶ RECEITAS | F3: Data | G3: Descrição | H3: Categoria | I3: Tipo | J3: Valor (R$)
A4: Categoria | B4: Orçado (R$) | C4: Realizado (R$) | D4: Diferença (R$)
A5: Salário | D5: =C5-B5
A6: Freelance / Extra | D6: =C6-B6
A7: Investimentos | D7: =C7-B7
A8: Outros (Receita) | D8: =C8-B8
A9: TOTAL RECEITAS | B9: =SUM(B5:B8) | C9: =SUM(C5:C8) | D9: =SUM(D5:D8)
A11: ▶ DESPESAS
A12: Categoria | B12: Orçado (R$) | C12: Realizado (R$) | D12: Diferença (R$)
A13: Moradia + Alimentação | D13: =B13-C13
A14: Transporte + Saúde | D14: =B14-C14
A15: Dívidas / Parcelas | D15: =B15-C15
A16: Outros (Despesa) | D16: =B16-C16
A17: TOTAL DESPESAS | B17: =SUM(B13:B16) | C17: =SUM(C13:C16) | D17: =SUM(D13:D16)
A19: ▶ SALDO DO MÊS
B20: Orçado (R$) | C20: Realizado (R$) | D20: Diferença (R$)
A21: Receitas − Despesas | B21: =B9-B17 | C21: =C9-C17 | D21: =D9-D17

Sheet Abr
A1: ORÇAMENTO — ABRIL 2026 | F1: LANÇAMENTOS — ABRIL 2026
F2: Preencha as colunas B e C (Orçado e Realizado) nos cards à esquerda
A3: ▶ RECEITAS | F3: Data | G3: Descrição | H3: Categoria | I3: Tipo | J3: Valor (R$)
A4: Categoria | B4: Orçado (R$) | C4: Realizado (R$) | D4: Diferença (R$)
A5: Salário | D5: =C5-B5
A6: Freelance / Extra | D6: =C6-B6
A7: Investimentos | D7: =C7-B7
A8: Outros (Receita) | D8: =C8-B8
A9: TOTAL RECEITAS | B9: =SUM(B5:B8) | C9: =SUM(C5:C8) | D9: =SUM(D5:D8)
A11: ▶ DESPESAS
A12: Categoria | B12: Orçado (R$) | C12: Realizado (R$) | D12: Diferença (R$)
A13: Moradia + Alimentação | D13: =B13-C13
A14: Transporte + Saúde | D14: =B14-C14
A15: Dívidas / Parcelas | D15: =B15-C15
A16: Outros (Despesa) | D16: =B16-C16
A17: TOTAL DESPESAS | B17: =SUM(B13:B16) | C17: =SUM(C13:C16) | D17: =SUM(D13:D16)
A19: ▶ SALDO DO MÊS
B20: Orçado (R$) | C20: Realizado (R$) | D20: Diferença (R$)
A21: Receitas − Despesas | B21: =B9-B17 | C21: =C9-C17 | D21: =D9-D17

Sheet Mai
A1: ORÇAMENTO — MAIO 2026 | F1: LANÇAMENTOS — MAIO 2026
F2: Preencha as colunas B e C (Orçado e Realizado) nos cards à esquerda
A3: ▶ RECEITAS | F3: Data | G3: Descrição | H3: Categoria | I3: Tipo | J3: Valor (R$)
A4: Categoria | B4: Orçado (R$) | C4: Realizado (R$) | D4: Diferença (R$)
A5: Salário | D5: =C5-B5
A6: Freelance / Extra | D6: =C6-B6
A7: Investimentos | D7: =C7-B7
A8: Outros (Receita) | D8: =C8-B8
A9: TOTAL RECEITAS | B9: =SUM(B5:B8) | C9: =SUM(C5:C8) | D9: =SUM(D5:D8)
A11: ▶ DESPESAS
A12: Categoria | B12: Orçado (R$) | C12: Realizado (R$) | D12: Diferença (R$)
A13: Moradia + Alimentação | D13: =B13-C13
A14: Transporte + Saúde | D14: =B14-C14
A15: Dívidas / Parcelas | D15: =B15-C15
A16: Outros (Despesa) | D16: =B16-C16
A17: TOTAL DESPESAS | B17: =SUM(B13:B16) | C17: =SUM(C13:C16) | D17: =SUM(D13:D16)
A19: ▶ SALDO DO MÊS
B20: Orçado (R$) | C20: Realizado (R$) | D20: Diferença (R$)
A21: Receitas − Despesas | B21: =B9-B17 | C21: =C9-C17 | D21: =D9-D17

Sheet Jun
A1: ORÇAMENTO — JUNHO 2026 | F1: LANÇAMENTOS — JUNHO 2026
F2: Preencha as colunas B e C (Orçado e Realizado) nos cards à esquerda
A3: ▶ RECEITAS | F3: Data | G3: Descrição | H3: Categoria | I3: Tipo | J3: Valor (R$)
A4: Categoria | B4: Orçado (R$) | C4: Realizado (R$) | D4: Diferença (R$)
A5: Salário | D5: =C5-B5
A6: Freelance / Extra | D6: =C6-B6
A7: Investimentos | D7: =C7-B7
A8: Outros (Receita) | D8: =C8-B8
A9: TOTAL RECEITAS | B9: =SUM(B5:B8) | C9: =SUM(C5:C8) | D9: =SUM(D5:D8)
A11: ▶ DESPESAS
A12: Categoria | B12: Orçado (R$) | C12: Realizado (R$) | D12: Diferença (R$)
A13: Moradia + Alimentação | D13: =B13-C13
A14: Transporte + Saúde | D14: =B14-C14
A15: Dívidas / Parcelas | D15: =B15-C15
A16: Outros (Despesa) | D16: =B16-C16
A17: TOTAL DESPESAS | B17: =SUM(B13:B16) | C17: =SUM(C13:C16) | D17: =SUM(D13:D16)
A19: ▶ SALDO DO MÊS
B20: Orçado (R$) | C20: Realizado (R$) | D20: Diferença (R$)
A21: Receitas − Despesas | B21: =B9-B17 | C21: =C9-C17 | D21: =D9-D17

Sheet Jul
A1: ORÇAMENTO — JULHO 2026 | F1: LANÇAMENTOS — JULHO 2026
F2: Preencha as colunas B e C (Orçado e Realizado) nos cards à esquerda
A3: ▶ RECEITAS | F3: Data | G3: Descrição | H3: Categoria | I3: Tipo | J3: Valor (R$)
A4: Categoria | B4: Orçado (R$) | C4: Realizado (R$) | D4: Diferença (R$)
A5: Salário | D5: =C5-B5
A6: Freelance / Extra | D6: =C6-B6
A7: Investimentos | D7: =C7-B7
A8: Outros (Receita) | D8: =C8-B8
A9: TOTAL RECEITAS | B9: =SUM(B5:B8) | C9: =SUM(C5:C8) | D9: =SUM(D5:D8)
A11: ▶ DESPESAS
A12: Categoria | B12: Orçado (R$) | C12: Realizado (R$) | D12: Diferença (R$)
A13: Moradia + Alimentação | D13: =B13-C13
A14: Transporte + Saúde | D14: =B14-C14
A15: Dívidas / Parcelas | D15: =B15-C15
A16: Outros (Despesa) | D16: =B16-C16
A17: TOTAL DESPESAS | B17: =SUM(B13:B16) | C17: =SUM(C13:C16) | D17: =SUM(D13:D16)
A19: ▶ SALDO DO MÊS
B20: Orçado (R$) | C20: Realizado (R$) | D20: Diferença (R$)
A21: Receitas − Despesas | B21: =B9-B17 | C21: =C9-C17 | D21: =D9-D17

Sheet Ago
A1: ORÇAMENTO — AGOSTO 2026 | F1: LANÇAMENTOS — AGOSTO 2026
F2: Preencha as colunas B e C (Orçado e Realizado) nos cards à esquerda
A3: ▶ RECEITAS | F3: Data | G3: Descrição | H3: Categoria | I3: Tipo | J3: Valor (R$)
A4: Categoria | B4: Orçado (R$) | C4: Realizado (R$) | D4: Diferença (R$)
A5: Salário | D5: =C5-B5
A6: Freelance / Extra | D6: =C6-B6
A7: Investimentos | D7: =C7-B7
A8: Outros (Receita) | D8: =C8-B8
A9: TOTAL RECEITAS | B9: =SUM(B5:B8) | C9: =SUM(C5:C8) | D9: =SUM(D5:D8)
A11: ▶ DESPESAS
A12: Categoria | B12: Orçado (R$) | C12: Realizado (R$) | D12: Diferença (R$)
A13: Moradia + Alimentação | D13: =B13-C13
A14: Transporte + Saúde | D14: =B14-C14
A15: Dívidas / Parcelas | D15: =B15-C15
A16: Outros (Despesa) | D16: =B16-C16
A17: TOTAL DESPESAS | B17: =SUM(B13:B16) | C17: =SUM(C13:C16) | D17: =SUM(D13:D16)
A19: ▶ SALDO DO MÊS
B20: Orçado (R$) | C20: Realizado (R$) | D20: Diferença (R$)
A21: Receitas − Despesas | B21: =B9-B17 | C21: =C9-C17 | D21: =D9-D17

Sheet Set
A1: ORÇAMENTO — SETEMBRO 2026 | F1: LANÇAMENTOS — SETEMBRO 2026
F2: Preencha as colunas B e C (Orçado e Realizado) nos cards à esquerda
A3: ▶ RECEITAS | F3: Data | G3: Descrição | H3: Categoria | I3: Tipo | J3: Valor (R$)
A4: Categoria | B4: Orçado (R$) | C4: Realizado (R$) | D4: Diferença (R$)
A5: Salário | D5: =C5-B5
A6: Freelance / Extra | D6: =C6-B6
A7: Investimentos | D7: =C7-B7
A8: Outros (Receita) | D8: =C8-B8
A9: TOTAL RECEITAS | B9: =SUM(B5:B8) | C9: =SUM(C5:C8) | D9: =SUM(D5:D8)
A11: ▶ DESPESAS
A12: Categoria | B12: Orçado (R$) | C12: Realizado (R$) | D12: Diferença (R$)
A13: Moradia + Alimentação | D13: =B13-C13
A14: Transporte + Saúde | D14: =B14-C14
A15: Dívidas / Parcelas | D15: =B15-C15
A16: Outros (Despesa) | D16: =B16-C16
A17: TOTAL DESPESAS | B17: =SUM(B13:B16) | C17: =SUM(C13:C16) | D17: =SUM(D13:D16)
A19: ▶ SALDO DO MÊS
B20: Orçado (R$) | C20: Realizado (R$) | D20: Diferença (R$)
A21: Receitas − Despesas | B21: =B9-B17 | C21: =C9-C17 | D21: =D9-D17

Sheet Out
A1: ORÇAMENTO — OUTUBRO 2026 | F1: LANÇAMENTOS — OUTUBRO 2026
F2: Preencha as colunas B e C (Orçado e Realizado) nos cards à esquerda
A3: ▶ RECEITAS | F3: Data | G3: Descrição | H3: Categoria | I3: Tipo | J3: Valor (R$)
A4: Categoria | B4: Orçado (R$) | C4: Realizado (R$) | D4: Diferença (R$)
A5: Salário | D5: =C5-B5
A6: Freelance / Extra | D6: =C6-B6
A7: Investimentos | D7: =C7-B7
A8: Outros (Receita) | D8: =C8-B8
A9: TOTAL RECEITAS | B9: =SUM(B5:B8) | C9: =SUM(C5:C8) | D9: =SUM(D5:D8)
A11: ▶ DESPESAS
A12: Categoria | B12: Orçado (R$) | C12: Realizado (R$) | D12: Diferença (R$)
A13: Moradia + Alimentação | D13: =B13-C13
A14: Transporte + Saúde | D14: =B14-C14
A15: Dívidas / Parcelas | D15: =B15-C15
A16: Outros (Despesa) | D16: =B16-C16
A17: TOTAL DESPESAS | B17: =SUM(B13:B16) | C17: =SUM(C13:C16) | D17: =SUM(D13:D16)
A19: ▶ SALDO DO MÊS
B20: Orçado (R$) | C20: Realizado (R$) | D20: Diferença (R$)
A21: Receitas − Despesas | B21: =B9-B17 | C21: =C9-C17 | D21: =D9-D17

Sheet Nov
A1: ORÇAMENTO — NOVEMBRO 2026 | F1: LANÇAMENTOS — NOVEMBRO 2026
F2: Preencha as colunas B e C (Orçado e Realizado) nos cards à esquerda
A3: ▶ RECEITAS | F3: Data | G3: Descrição | H3: Categoria | I3: Tipo | J3: Valor (R$)
A4: Categoria | B4: Orçado (R$) | C4: Realizado (R$) | D4: Diferença (R$)
A5: Salário | D5: =C5-B5
A6: Freelance / Extra | D6: =C6-B6
A7: Investimentos | D7: =C7-B7
A8: Outros (Receita) | D8: =C8-B8
A9: TOTAL RECEITAS | B9: =SUM(B5:B8) | C9: =SUM(C5:C8) | D9: =SUM(D5:D8)
A11: ▶ DESPESAS
A12: Categoria | B12: Orçado (R$) | C12: Realizado (R$) | D12: Diferença (R$)
A13: Moradia + Alimentação | D13: =B13-C13
A14: Transporte + Saúde | D14: =B14-C14
A15: Dívidas / Parcelas | D15: =B15-C15
A16: Outros (Despesa) | D16: =B16-C16
A17: TOTAL DESPESAS | B17: =SUM(B13:B16) | C17: =SUM(C13:C16) | D17: =SUM(D13:D16)
A19: ▶ SALDO DO MÊS
B20: Orçado (R$) | C20: Realizado (R$) | D20: Diferença (R$)
A21: Receitas − Despesas | B21: =B9-B17 | C21: =C9-C17 | D21: =D9-D17

Sheet Dez
A1: ORÇAMENTO — DEZEMBRO 2026 | F1: LANÇAMENTOS — DEZEMBRO 2026
F2: Preencha as colunas B e C (Orçado e Realizado) nos cards à esquerda
A3: ▶ RECEITAS | F3: Data | G3: Descrição | H3: Categoria | I3: Tipo | J3: Valor (R$)
A4: Categoria | B4: Orçado (R$) | C4: Realizado (R$) | D4: Diferença (R$)
A5: Salário | D5: =C5-B5
A6: Freelance / Extra | D6: =C6-B6
A7: Investimentos | D7: =C7-B7
A8: Outros (Receita) | D8: =C8-B8
A9: TOTAL RECEITAS | B9: =SUM(B5:B8) | C9: =SUM(C5:C8) | D9: =SUM(D5:D8)
A11: ▶ DESPESAS
A12: Categoria | B12: Orçado (R$) | C12: Realizado (R$) | D12: Diferença (R$)
A13: Moradia + Alimentação | D13: =B13-C13
A14: Transporte + Saúde | D14: =B14-C14
A15: Dívidas / Parcelas | D15: =B15-C15
A16: Outros (Despesa) | D16: =B16-C16
A17: TOTAL DESPESAS | B17: =SUM(B13:B16) | C17: =SUM(C13:C16) | D17: =SUM(D13:D16)
A19: ▶ SALDO DO MÊS
B20: Orçado (R$) | C20: Realizado (R$) | D20: Diferença (R$)
A21: Receitas − Despesas | B21: =B9-B17 | C21: =C9-C17 | D21: =D9-D17
